{"otherData": {},"traceEvents":[{"cat":"function","dur":30553,"name":"glfwInit","ph":"X","pid":0,"tid":2783254248,"ts":682303922090},{"cat":"function","dur":478240,"name":"glfwCreateWindow","ph":"X","pid":0,"tid":2783254248,"ts":682303953515},{"cat":"function","dur":3907,"name":"void __cdecl Prism::OpenGLContext::Initialize(void)","ph":"X","pid":0,"tid":2783254248,"ts":682304451311},{"cat":"function","dur":26,"name":"void __cdecl Prism::WindowsWindow::SetVSync(bool)","ph":"X","pid":0,"tid":2783254248,"ts":682304455307},{"cat":"function","dur":533883,"name":"void __cdecl Prism::WindowsWindow::Initialize(const struct Prism::WindowProperties &)","ph":"X","pid":0,"tid":2783254248,"ts":682303921496},{"cat":"function","dur":533928,"name":"__cdecl Prism::WindowsWindow::WindowsWindow(const struct Prism::WindowProperties &)","ph":"X","pid":0,"tid":2783254248,"ts":682303921490},{"cat":"function","dur":18,"name":"void __cdecl Prism::WindowsWindow::SetVSync(bool)","ph":"X","pid":0,"tid":2783254248,"ts":682304455474},{"cat":"function","dur":9,"name":"void __cdecl Prism::OpenGLRendererAPI::InitializeRenderer(void)","ph":"X","pid":0,"tid":2783254248,"ts":682304455766},{"cat":"function","dur":32,"name":"__cdecl Prism::OpenGLVertexArray::OpenGLVertexArray(void)","ph":"X","pid":0,"tid":2783254248,"ts":682304455847},{"cat":"function","dur":20,"name":"__cdecl Prism::OpenGLVertexBuffer::OpenGLVertexBuffer(unsigned int)","ph":"X","pid":0,"tid":2783254248,"ts":682304455946},{"cat":"function","dur":1,"name":"void __cdecl Prism::OpenGLVertexBuffer::BindVertexBuffer(void) const","ph":"X","pid":0,"tid":2783254248,"ts":682304456081},{"cat":"function","dur":87,"name":"void __cdecl Prism::OpenGLVertexArray::AddVertexBuffer(class std::shared_ptr<class Prism::VertexBuffer> &)","ph":"X","pid":0,"tid":2783254248,"ts":682304456040},{"cat":"function","dur":553,"name":"__cdecl Prism::OpenGLIndexBuffer::OpenGLIndexBuffer(unsigned int *,unsigned int)","ph":"X","pid":0,"tid":2783254248,"ts":682304459043},{"cat":"function","dur":1,"name":"void __cdecl Prism::OpenGLIndexBuffer::BindIndexBuffer(void) const","ph":"X","pid":0,"tid":2783254248,"ts":682304459686},{"cat":"function","dur":45,"name":"void __cdecl Prism::OpenGLVertexArray::SetIndexBuffer(class std::shared_ptr<class Prism::IndexBuffer> &)","ph":"X","pid":0,"tid":2783254248,"ts":682304459681},{"cat":"function","dur":42,"name":"__cdecl Prism::OpenGLTexture2D::OpenGLTexture2D(unsigned int,unsigned int)","ph":"X","pid":0,"tid":2783254248,"ts":682304459840},{"cat":"function","dur":14,"name":"void __cdecl Prism::OpenGLTexture2D::SetTextureData(void *,unsigned int)","ph":"X","pid":0,"tid":2783254248,"ts":682304459945},{"cat":"function","dur":371,"name":"class std::basic_string<char,struct std::char_traits<char>,class std::allocator<char> > __cdecl Prism::OpenGLShader::ReadFile(const class std::basic_string<char,struct std::char_traits<char>,class std::allocator<char> > &)","ph":"X","pid":0,"tid":2783254248,"ts":682304460224},{"cat":"function","dur":218,"name":"class std::unordered_map<unsigned int,class std::basic_string<char,struct std::char_traits<char>,class std::allocator<char> >,struct std::hash<unsigned int>,struct std::equal_to<unsigned int>,class std::allocator<struct std::pair<unsigned int const ,class std::basic_string<char,struct std::char_traits<char>,class std::allocator<char> > > > > __cdecl Prism::OpenGLShader::PreProcessFile(const class std::basic_string<char,struct std::char_traits<char>,class std::allocator<char> > &)","ph":"X","pid":0,"tid":2783254248,"ts":682304460653},{"cat":"function","dur":3462,"name":"void __cdecl Prism::OpenGLShader::CompileShader(class std::unordered_map<unsigned int,class std::basic_string<char,struct std::char_traits<char>,class std::allocator<char> >,struct std::hash<unsigned int>,struct std::equal_to<unsigned int>,class std::allocator<struct std::pair<unsigned int const ,class std::basic_string<char,struct std::char_traits<char>,class std::allocator<char> > > > > &)","ph":"X","pid":0,"tid":2783254248,"ts":682304460925},{"cat":"function","dur":4315,"name":"__cdecl Prism::OpenGLShader::OpenGLShader(const class std::basic_string<char,struct std::char_traits<char>,class std::allocator<char> > &)","ph":"X","pid":0,"tid":2783254248,"ts":682304460210},{"cat":"function","dur":4,"name":"void __cdecl Prism::OpenGLShader::BindShader(void) const","ph":"X","pid":0,"tid":2783254248,"ts":682304464686},{"cat":"function","dur":47,"name":"void __cdecl Prism::OpenGLShader::SetShaderIntegerArray(const class std::basic_string<char,struct std::char_traits<char>,class std::allocator<char> > &,int *,unsigned int)","ph":"X","pid":0,"tid":2783254248,"ts":682304464765},{"cat":"function","dur":9051,"name":"void __cdecl Prism::Renderer2D::Initialize2DRenderer(void)","ph":"X","pid":0,"tid":2783254248,"ts":682304455827},{"cat":"function","dur":9159,"name":"void __cdecl Prism::Renderer::InitializeRenderer(void)","ph":"X","pid":0,"tid":2783254248,"ts":682304455758},{"cat":"function","dur":1309,"name":"void __cdecl Prism::ImGuiLayer::OnAttach(void)","ph":"X","pid":0,"tid":2783254248,"ts":682304465315},{"cat":"function","dur":1385,"name":"void __cdecl Prism::Application::PushOverlay(class Prism::Layer *)","ph":"X","pid":0,"tid":2783254248,"ts":682304465295},{"cat":"function","dur":545241,"name":"__cdecl Prism::Application::Application(const class std::basic_string<char,struct std::char_traits<char>,class std::allocator<char> > &)","ph":"X","pid":0,"tid":2783254248,"ts":682303921477},{"cat":"function","dur":14,"name":"__cdecl Prism::OrthographicCamera::OrthographicCamera(float,float,float,float)","ph":"X","pid":0,"tid":2783254248,"ts":682304466926},{"cat":"function","dur":148,"name":"stbi_load - OpenGLTexture2D::OpenGLTexture2D(const std::string& filePath)","ph":"X","pid":0,"tid":2783254248,"ts":682304467018},{"cat":"function","dur":221,"name":"__cdecl Prism::OpenGLTexture2D::OpenGLTexture2D(const class std::basic_string<char,struct std::char_traits<char>,class std::allocator<char> >)","ph":"X","pid":0,"tid":2783254248,"ts":682304467013},{"cat":"function","dur":118,"name":"stbi_load - OpenGLTexture2D::OpenGLTexture2D(const std::string& filePath)","ph":"X","pid":0,"tid":2783254248,"ts":682304467288},{"cat":"function","dur":212,"name":"__cdecl Prism::OpenGLTexture2D::OpenGLTexture2D(const class std::basic_string<char,struct std::char_traits<char>,class std::allocator<char> >)","ph":"X","pid":0,"tid":2783254248,"ts":682304467284},{"cat":"function","dur":118,"name":"stbi_load - OpenGLTexture2D::OpenGLTexture2D(const std::string& filePath)","ph":"X","pid":0,"tid":2783254248,"ts":682304467549},{"cat":"function","dur":204,"name":"__cdecl Prism::OpenGLTexture2D::OpenGLTexture2D(const class std::basic_string<char,struct std::char_traits<char>,class std::allocator<char> >)","ph":"X","pid":0,"tid":2783254248,"ts":682304467544},{"cat":"function","dur":141,"name":"stbi_load - OpenGLTexture2D::OpenGLTexture2D(const std::string& filePath)","ph":"X","pid":0,"tid":2783254248,"ts":682304468246},{"cat":"function","dur":235,"name":"__cdecl Prism::OpenGLTexture2D::OpenGLTexture2D(const class std::basic_string<char,struct std::char_traits<char>,class std::allocator<char> >)","ph":"X","pid":0,"tid":2783254248,"ts":682304468242},{"cat":"function","dur":2206,"name":"void __cdecl Prism::EditorLayer::OnAttach(void)","ph":"X","pid":0,"tid":2783254248,"ts":682304468234},{"cat":"function","dur":2331,"name":"void __cdecl Prism::Application::PushLayer(class Prism::Layer *)","ph":"X","pid":0,"tid":2783254248,"ts":682304468224}]}